tgshops_integrations/__init__.py
tgshops_integrations/middlewares/__init__.py
tgshops_integrations/middlewares/gateway.py
tgshops_integrations/models/__init__.py
tgshops_integrations/models/categories.py
tgshops_integrations/models/products.py
tgshops_integrations/nocodb_connector/__init__.py
tgshops_integrations/nocodb_connector/categories_management.py
tgshops_integrations/nocodb_connector/client.py
tgshops_integrations/nocodb_connector/model_mapping.py
tgshops_integrations/nocodb_connector/products_management.py
tgshops_integrations/nocodb_connector/tables.py
tgshops_integrations-5.0.dist-info/METADATA
tgshops_integrations-5.0.dist-info/WHEEL
tgshops_integrations-5.0.dist-info/top_level.txt
tgshops_integrations-5.0.dist-info/RECORD
