Metadata-Version: 2.1
Name: tgshops-integrations
Version: 5.0
Summary: Library is intended to provide the integration of the external service or CRM system with the TelegramShops/It allows to configure the relationship between NocoDB list of the products used further to display in the shop/As a resultss the products can be synchronized and updated uppon the request.
Home-page: https://git.the-devs.com/virtual-shops/shop-system/shop-backend-integrations/integration-library/integration-library
Author: Dimi Latoff
Author-email: drpozd@gmail.com
License: MIT
Classifier: Programming Language :: Python :: 3
Classifier: License :: OSI Approved :: MIT License
Classifier: Operating System :: OS Independent
Requires-Python: >=3.10
